.gitignore
.gitmodules
Dockerfile
LICENSE
README.md
requirements.txt
setup.py
docs/Makefile
docs/conf.py
docs/config.rst
docs/index.rst
docs/make.bat
docs/reference.rst
docs/requirements.txt
examples/ackley.py
examples/example.py
examples/modules.py
gifs/lunarlander.gif
nes/MPI.py
nes/__init__.py
nes/config.py
nes/nes.py
nes/utils.py
nes/dataclass_config/__init__.py
nes/dataclass_config/dataclass_config.py
nes_torch.egg-info/PKG-INFO
nes_torch.egg-info/SOURCES.txt
nes_torch.egg-info/dependency_links.txt
nes_torch.egg-info/requires.txt
nes_torch.egg-info/top_level.txt