Metadata-Version: 2.1
Name: nes-torch
Version: 2.1.0
Summary: Minimal PyTorch Library for Natural Evolution Strategies
Home-page: https://github.com/goktug97/nes-torch
Author: Göktuğ Karakaşlı
Author-email: karakasligk@gmail.com
License: MIT
Platform: UNKNOWN
Classifier: Programming Language :: Python :: 3
Classifier: License :: OSI Approved :: MIT License
Requires-Python: >=3.7
License-File: LICENSE
